xxxsssssasdasdasdasd/__init__.py
xxxsssssasdasdasdasd/s3_bucket.py
xxxsssssasdasdasdasd-0.1.3.dist-info/METADATA
xxxsssssasdasdasdasd-0.1.3.dist-info/WHEEL
xxxsssssasdasdasdasd-0.1.3.dist-info/RECORD
