Metadata-Version: 2.1
Name: xxxsssssasdasdasdasd
Version: 0.1.3
Summary: 
Author: Your Name
Author-email: you@example.com
Requires-Python: >=3.12,<4.0
Classifier: Programming Language :: Python :: 3
Classifier: Programming Language :: Python :: 3.12
Requires-Dist: aws-cdk-lib (>=2.153.0,<3.0.0)
Requires-Dist: pytest (>=8.3.2,<9.0.0)
Requires-Dist: twine (>=5.1.1,<6.0.0)
